SegJJC/__init__.py
SegJJC/train_cls_ori.py
SegJJC/train_json_solo.py
SegJJC/train_jsonit.py
SegJJC/EfficientNet/__init__.py
SegJJC/EfficientNet/train_cls.py
SegJJC/EfficientNet/efficientnet_pytorch/__init__.py
SegJJC/EfficientNet/efficientnet_pytorch/model.py
SegJJC/EfficientNet/efficientnet_pytorch/transforms_cls.py
SegJJC/EfficientNet/efficientnet_pytorch/utils.py
SegJJC/demo/DoAi.py
SegJJC/demo/cfg2.0.json
SegJJC/demo/cfg_export.json
SegJJC/demo/cfg_test.json
SegJJC/demo/cfg_train.json
SegJJC/demo/doai_export.py
SegJJC/demo/doai_test.py
SegJJC/demo/doai_train.py
SegJJC/dll/halcon.dll
SegJJC/dll/halconxl.dll
SegJJC/fcn/VOC_seg_data.py
SegJJC/fcn/__init__.py
SegJJC/fcn/get_palette.py
SegJJC/fcn/my_dataset.py
SegJJC/fcn/palette.json
SegJJC/fcn/palettit.py
SegJJC/fcn/pascal_voc_classes.json
SegJJC/fcn/predict.py
SegJJC/fcn/requirements.txt
SegJJC/fcn/train.py
SegJJC/fcn/train_multi_GPU.py
SegJJC/fcn/transforms.py
SegJJC/fcn/validation.py
SegJJC/fcn/src/__init__.py
SegJJC/fcn/src/backbone.py
SegJJC/fcn/src/deeplabv3_model.py
SegJJC/fcn/src/fcn_model.py
SegJJC/fcn/train_utils/__init__.py
SegJJC/fcn/train_utils/distributed_utils.py
SegJJC/fcn/train_utils/train_and_eval.py
SegJJC/othermodules/Hsahi.py
SegJJC/othermodules/ROI_t.py
SegJJC/othermodules/__init__.py
SegJJC/othermodules/autolabel.py
SegJJC/othermodules/enlarge_label.py
SegJJC/othermodules/enlarge_label_gui.py
SegJJC/othermodules/export.py
SegJJC/othermodules/gen_wts.py
SegJJC/othermodules/jsonvert.py
SegJJC/othermodules/predict.py
SegJJC/othermodules/predict_seg.py
SegJJC-0.0.18.dist-info/METADATA
SegJJC-0.0.18.dist-info/WHEEL
SegJJC-0.0.18.dist-info/dependency_links.txt
SegJJC-0.0.18.dist-info/top_level.txt
SegJJC-0.0.18.dist-info/RECORD
