Metadata-Version: 2.1
Name: SegJJC
Version: 0.0.18
Summary: A AI train Python package of JJC for Detect,seg,classify
Home-page: https://gitee.com/hfh936784552/Segjjc_git
Author: hfh
Author-email: your.email@example.com
Classifier: Programming Language :: Python :: 3
Classifier: License :: OSI Approved :: MIT License
Classifier: Operating System :: OS Independent
Requires-Python: >=3.8
Requires-Dist: ultralytics >=8.3.104
Requires-Dist: mvtec-halcon ==24050
Requires-Dist: onnxruntime >=1.18.0
